{
  "tool": "build_iiis1.sh",
  "ported_tus": "acc,ast,ceiling,cg_r0,cg_r3,cg_rm1,cg_rm2,cg_sha,emit,hexad_check,jit_emit,lex,lex_rt,link,main,parse,proof,sema,sid,witness_alloc",
  "mode": "release",
  "iiis0_used": "iiis-1.exe",
  "output": "iiis-2.exe",
  "source_files": ["cg_r3_xii.c","cg_r3_xii_adapter.c","emit_accessors.c","iiis1_link_stubs.c","iii_cg_pe_iiis1.c","lex_runtime.c","sema_xii.c","sema_xii_adapter.c","xii_lattice_loader.c","xii_ldil.c"],
  "output_mhash": "15155fb5a240134cc3c69870eaef45e3853609badb4c74a06e6c604a584b5a38"
}
